<profile>

<ReportVersion>
<Version>2020.2</Version>
</ReportVersion>

<UserAssignments>
<unit>ns</unit>
<ProductFamily>virtexuplus</ProductFamily>
<Part>xcvu3p-ffvc1517-3-e</Part>
<TopModelName>td_fused_axi_in_top</TopModelName>
<TargetClockPeriod>3.00</TargetClockPeriod>
<ClockUncertainty>0.81</ClockUncertainty>
<FlowTarget>vivado</FlowTarget>
</UserAssignments>

<PerformanceEstimates>
<PipelineType>none</PipelineType>
<SummaryOfTimingAnalysis>
<unit>ns</unit>
<EstimatedClockPeriod>1.779</EstimatedClockPeriod>
</SummaryOfTimingAnalysis>
<SummaryOfOverallLatency>
<unit>clock cycles</unit>
<Best-caseLatency>150531</Best-caseLatency>
<Average-caseLatency>150531</Average-caseLatency>
<Worst-caseLatency>150531</Worst-caseLatency>
<Best-caseRealTimeLatency>0.452 ms</Best-caseRealTimeLatency>
<Average-caseRealTimeLatency>0.452 ms</Average-caseRealTimeLatency>
<Worst-caseRealTimeLatency>0.452 ms</Worst-caseRealTimeLatency>
<Interval-min>150532</Interval-min>
<Interval-max>150532</Interval-max>
</SummaryOfOverallLatency>
<SummaryOfLoopLatency>
<VITIS_LOOP_17_1_VITIS_LOOP_18_2_VITIS_LOOP_20_3>
<TripCount>150528</TripCount>
<Latency>150528</Latency>
<AbsoluteTimeLatency>451584</AbsoluteTimeLatency>
<PipelineII>1</PipelineII>
<PipelineDepth>2</PipelineDepth>
</VITIS_LOOP_17_1_VITIS_LOOP_18_2_VITIS_LOOP_20_3>
</SummaryOfLoopLatency>
</PerformanceEstimates>

<AreaEstimates>
<Resources>
<FF>118</FF>
<LUT>344</LUT>
<URAM>13</URAM>
<BRAM_18K>0</BRAM_18K>
<DSP>0</DSP>
</Resources>
<AvailableResources>
<BRAM_18K>1440</BRAM_18K>
<DSP>2280</DSP>
<FF>788160</FF>
<LUT>394080</LUT>
<URAM>320</URAM>
</AvailableResources>
</AreaEstimates>

<InterfaceSummary>
<RtlPorts>
<name>ap_clk</name>
<Object>td_fused_axi_in_top</Object>
<Type>return value</Type>
<Scope></Scope>
<IOProtocol>ap_ctrl_hs</IOProtocol>
<IOConfig></IOConfig>
<Dir>in</Dir>
<Bits>1</Bits>
<Attribute>control</Attribute>
</RtlPorts>
<RtlPorts>
<name>ap_rst_n</name>
<Object>td_fused_axi_in_top</Object>
<Type>return value</Type>
<Scope></Scope>
<IOProtocol>ap_ctrl_hs</IOProtocol>
<IOConfig></IOConfig>
<Dir>in</Dir>
<Bits>1</Bits>
<Attribute>control</Attribute>
</RtlPorts>
<RtlPorts>
<name>ap_start</name>
<Object>td_fused_axi_in_top</Object>
<Type>return value</Type>
<Scope></Scope>
<IOProtocol>ap_ctrl_hs</IOProtocol>
<IOConfig></IOConfig>
<Dir>in</Dir>
<Bits>1</Bits>
<Attribute>control</Attribute>
</RtlPorts>
<RtlPorts>
<name>ap_done</name>
<Object>td_fused_axi_in_top</Object>
<Type>return value</Type>
<Scope></Scope>
<IOProtocol>ap_ctrl_hs</IOProtocol>
<IOConfig></IOConfig>
<Dir>out</Dir>
<Bits>1</Bits>
<Attribute>control</Attribute>
</RtlPorts>
<RtlPorts>
<name>ap_idle</name>
<Object>td_fused_axi_in_top</Object>
<Type>return value</Type>
<Scope></Scope>
<IOProtocol>ap_ctrl_hs</IOProtocol>
<IOConfig></IOConfig>
<Dir>out</Dir>
<Bits>1</Bits>
<Attribute>control</Attribute>
</RtlPorts>
<RtlPorts>
<name>ap_ready</name>
<Object>td_fused_axi_in_top</Object>
<Type>return value</Type>
<Scope></Scope>
<IOProtocol>ap_ctrl_hs</IOProtocol>
<IOConfig></IOConfig>
<Dir>out</Dir>
<Bits>1</Bits>
<Attribute>control</Attribute>
</RtlPorts>
<RtlPorts>
<name>ap_return</name>
<Object>td_fused_axi_in_top</Object>
<Type>return value</Type>
<Scope></Scope>
<IOProtocol>ap_ctrl_hs</IOProtocol>
<IOConfig></IOConfig>
<Dir>out</Dir>
<Bits>16</Bits>
<Attribute>data</Attribute>
</RtlPorts>
<RtlPorts>
<name>stream_in_TDATA</name>
<Object>stream_in_V_data_V</Object>
<Type>pointer</Type>
<Scope></Scope>
<IOProtocol>axis</IOProtocol>
<IOConfig>register, both mode</IOConfig>
<Dir>in</Dir>
<Bits>16</Bits>
<Attribute>data</Attribute>
<CType>int</CType>
</RtlPorts>
<RtlPorts>
<name>stream_in_TVALID</name>
<Object>stream_in_V_last_V</Object>
<Type>pointer</Type>
<Scope></Scope>
<IOProtocol>axis</IOProtocol>
<IOConfig>register, both mode</IOConfig>
<Dir>in</Dir>
<Bits>1</Bits>
<Attribute>control</Attribute>
<CType>int</CType>
</RtlPorts>
<RtlPorts>
<name>stream_in_TREADY</name>
<Object>stream_in_V_last_V</Object>
<Type>pointer</Type>
<Scope></Scope>
<IOProtocol>axis</IOProtocol>
<IOConfig>register, both mode</IOConfig>
<Dir>out</Dir>
<Bits>1</Bits>
<Attribute>control</Attribute>
<CType>int</CType>
</RtlPorts>
<RtlPorts>
<name>stream_in_TLAST</name>
<Object>stream_in_V_last_V</Object>
<Type>pointer</Type>
<Scope></Scope>
<IOProtocol>axis</IOProtocol>
<IOConfig>register, both mode</IOConfig>
<Dir>in</Dir>
<Bits>1</Bits>
<Attribute>data</Attribute>
<CType>int</CType>
</RtlPorts>
<RtlPorts>
<name>stream_in_TKEEP</name>
<Object>stream_in_V_keep_V</Object>
<Type>pointer</Type>
<Scope></Scope>
<IOProtocol>axis</IOProtocol>
<IOConfig>register, both mode</IOConfig>
<Dir>in</Dir>
<Bits>2</Bits>
<Attribute>data</Attribute>
<CType>int</CType>
</RtlPorts>
<RtlPorts>
<name>stream_in_TSTRB</name>
<Object>stream_in_V_strb_V</Object>
<Type>pointer</Type>
<Scope></Scope>
<IOProtocol>axis</IOProtocol>
<IOConfig>register, both mode</IOConfig>
<Dir>in</Dir>
<Bits>2</Bits>
<Attribute>data</Attribute>
<CType>int</CType>
</RtlPorts>
</InterfaceSummary>

</profile>
