{"latency": 1003575, "true_latency": 1003575, "cost_info": {"bram": 0.0020833333333333333, "dsp": 0.008771929824561403, "ff": 0.004254212342671539, "lut": 0.01202547706049533, "uram": 0.04375, "total": 0.0708849525610616}, "subfunctions": [{"name": "tdf3_readInputs", "latency": 18}, {"name": "tdf3_accum_1", "latency": 13}, {"name": "tdf3_accum_2", "latency": 7}, {"name": "tdf3_adjust", "latency": 6}, {"name": "tdf3_dot_product", "latency": 19}, {"name": "tdf3_accum_3", "latency": 9}, {"name": "tdf3_readFilters", "latency": 18}]}